nexus/__init__.py
nexus/adapter.py
nexus/cli.py
nexus/schemas.py
nexus/core/__init__.py
nexus/core/engine.py
nexus_governance-0.1.0.dist-info/METADATA
nexus_governance-0.1.0.dist-info/WHEEL
nexus_governance-0.1.0.dist-info/entry_points.txt
nexus_governance-0.1.0.dist-info/RECORD
