Metadata-Version: 2.4
Name: nexus-governance
Version: 0.1.0
Summary: The Sudo Command for AI Agents. Local governance, atomic locking, and stable fingerprinting for MCP tools.
Project-URL: Homepage, https://github.com/zishanneno/nexus-governance
Author-email: Zishan Neno <7735088+zishanneno@users.noreply.github.com>
License: MIT
Keywords: agents,ai,governance,llm,mcp,security
Requires-Python: >=3.10
Requires-Dist: mcp[cli]>=0.1.0
Requires-Dist: pydantic>=2.0.0
Requires-Dist: textual>=0.40.0
